Workbook

Sheet Legend & Instructions
B2: Investment Analysis Tracker
B3: Buffett-Style Valuation Zone Dashboard
B5: VALUATION ZONE COLOR LEGEND
B7: Deep Value / Strong Buy | C7: Price is significantly below conservative intrinsic value. Maximum margin of safety. Fat pitch.
B8: Value / Buy | C8: Price is below fair value with adequate margin of safety. Good entry point for long-term investors.
B9: Fair Value / Hold | C9: Price is around intrinsic value. Hold if owned, don't initiate new positions. No margin of safety.
B10: Fully Valued / Trim | C10: Price exceeds base-case intrinsic value. Consider trimming. Downside risk exceeds upside.
B11: Overvalued / Sell | C11: Price is significantly above all intrinsic value estimates. Sell or avoid. Negative returns likely.
B12: Weak Business / Never Buy | C12: Fundamentally broken business. No price is cheap enough. Fails core Buffett quality criteria.
B15: HOW TO USE THIS WORKBOOK
B17: Step 1: Enter Current Prices | C17: Go to 'All Companies' sheet. Enter today's stock price in the 'Current Price' column (F). Zone + colors update automatically.
B19: Step 2: Excel Stocks (Optional) | C19: Select ticker cells (col C) > Data tab > Stocks. Excel links to live data. Then use =C3.Price in col F for auto prices.
B21: Step 3: Read Zone Colors | C21: Entire rows auto-color based on which valuation zone the current price falls in. Green = buy, Red = avoid.
B23: Step 4: Category Sheets | C23: Each zone has its own sheet with a FILTER formula. Companies auto-appear/disappear as their zone changes with price.
B25: Step 5: Add New Companies | C25: Add rows at the bottom of 'All Companies'. Fill zone boundaries. Update FILTER range in category sheets if needed.
B28: IMPORTANT NOTES
B30: All intrinsic values are estimates based on Buffett-style analysis. They are NOT price targets.
B31: Zone boundaries are derived from DCF, relative valuation, and margin-of-safety frameworks.
B32: Quality Score reflects business quality (moat, management, financials) - NOT valuation attractiveness.
B33: A high quality score + Deep Value zone = highest conviction opportunity.
B34: Prices and valuations are from the date of analysis. Re-evaluate if fundamentals change materially.
B35: This is NOT financial advice. Do your own due diligence before investing.

Sheet All Companies
A1: Investment Analysis Tracker - Buffett Valuation Zones
A2: Sr. | B2: Company Name | C2: Ticker | D2: Exchange | E2: Quality | F2: Current Price (Rs) | G2: Deep Value Below (Rs) | H2: Value/Buy Up To (Rs) | I2: Fair Value Up To (Rs) | J2: Overvalued Above (Rs) | K2: Conservative IV (Rs) | L2: Base Case IV (Rs) | M2: Optimistic IV (Rs) | N2: Current Zone | O2: Upside to Base IV (%) | P2: Key Notes
A3: 1 | B3: Asian Paints | C3: ASIANPAINT | D3: NSE | E3: 8.6/10 | G3: 645 | H3: 922 | I3: 1198 | J3: 1638 | K3: 922 | L3: 1198 | M3: 1638 | N3: =IF(F3="","Enter Price",IF(F3<=G3,"Deep Value / Strong Buy",IF(F3<=H3,"Value / Buy",IF(F3<=I3,"Fair Value / Hold",IF(F3<=J3,"Fully Valued / Trim","Overvalued / Sell"))))) -> 0 | O3: =IF(OR(F3="",F3=0),"N/A",ROUND((L3-F3)/F3*100,1)) -> 0 | P3: India's finest paint franchise; 62x PE vs IV ₹922-1,638; AVOID, buy below ₹922
A4: 2 | B4: Berger Paints India | C4: BERGEPAINT | D4: NSE | E4: 6.9/10 | G4: 240 | H4: 336 | I4: 432 | J4: 528 | K4: 210 | L4: 310 | M4: 399 | N4: =IF(F4="","Enter Price",IF(F4<=G4,"Deep Value / Strong Buy",IF(F4<=H4,"Value / Buy",IF(F4<=I4,"Fair Value / Hold",IF(F4<=J4,"Fully Valued / Trim","Overvalued / Sell"))))) -> 0 | O4: =IF(OR(F4="",F4=0),"N/A",ROUND((L4-F4)/F4*100,1)) -> 0 | P4: India #2 paint co; high-quality franchise but overvalued at ₹450; wait for ₹240-310
A5: 3 | B5: Kansai Nerolac Paints | C5: KANSAINER | D5: NSE | E5: 5.6/10 | G5: 100 | H5: 135 | I5: 165 | J5: 200 | K5: 136 | L5: 178 | M5: 211 | N5: =IF(F5="","Enter Price",IF(F5<=G5,"Deep Value / Strong Buy",IF(F5<=H5,"Value / Buy",IF(F5<=I5,"Fair Value / Hold",IF(F5<=J5,"Fully Valued / Trim","Overvalued / Sell"))))) -> 0 | O5: =IF(OR(F5="",F5=0),"N/A",ROUND((L5-F5)/F5*100,1)) -> 0 | P5: #3 paint player with eroding moat; fully valued near Base IV ₹178; buy below ₹135
A6: 4 | B6: Indigo Paints | C6: INDIGOPNTS | D6: NSE | E6: 7.0/10 | G6: 550 | H6: 670 | I6: 850 | J6: 1065 | K6: 774 | L6: 929 | M6: 1207 | N6: =IF(F6="","Enter Price",IF(F6<=G6,"Deep Value / Strong Buy",IF(F6<=H6,"Value / Buy",IF(F6<=I6,"Fair Value / Hold",IF(F6<=J6,"Fully Valued / Trim","Overvalued / Sell"))))) -> 0 | O6: =IF(OR(F6="",F6=0),"N/A",ROUND((L6-F6)/F6*100,1)) -> 0 | P6: Niche paint co with narrow eroding moat; Birla Opus pressure; wait for ₹550-650
A7: 5 | B7: Sirca Paints India | C7: SIRCA | D7: NSE | E7: 7.4/10 | G7: 220 | H7: 308 | I7: 396 | J7: 550 | K7: 366 | L7: 442 | M7: 658 | N7: =IF(F7="","Enter Price",IF(F7<=G7,"Deep Value / Strong Buy",IF(F7<=H7,"Value / Buy",IF(F7<=I7,"Fair Value / Hold",IF(F7<=J7,"Fully Valued / Trim","Overvalued / Sell"))))) -> 0 | O7: =IF(OR(F7="",F7=0),"N/A",ROUND((L7-F7)/F7*100,1)) -> 0 | P7: Good niche wood-coatings business; fully priced with zero MoS; fat-pitch entry ₹275-315
A8: 6 | B8: Shalimar Paints | C8: SHALPAINTS | D8: NSE | E8: 1.6/10 | G8: 0 | H8: 0 | I8: 0 | J8: 49 | K8: 0 | L8: 22 | M8: 35 | N8: Weak Business | O8: =IF(OR(F8="",F8=0),"N/A",ROUND((L8-F8)/F8*100,1)) -> 0 | P8: Value trap; chronic losses, no moat, eroding equity; STRONG AVOID at any price
A9: 7 | B9: JSW Dulux | C9: JSWDULUX | D9: NSE | E9: 7.8/10 | G9: 1440 | H9: 2016 | I9: 2520 | J9: 3240 | K9: 1071 | L9: 1451 | M9: 2082 | N9: =IF(F9="","Enter Price",IF(F9<=G9,"Deep Value / Strong Buy",IF(F9<=H9,"Value / Buy",IF(F9<=I9,"Fair Value / Hold",IF(F9<=J9,"Fully Valued / Trim","Overvalued / Sell"))))) -> 0 | O9: =IF(OR(F9="",F9=0),"N/A",ROUND((L9-F9)/F9*100,1)) -> 0 | P9: Elite 42% ROCE paint franchise; at 2x IV post-divestment; watchlist ₹1,440-1,800
A10: 8 | B10: Britannia Industries | C10: BRITANNIA | D10: NSE | E10: 8.7/10 | G10: 2700 | H10: 3600 | I10: 5000 | J10: 5900 | K10: 2030 | L10: 2369 | M10: 3281 | N10: =IF(F10="","Enter Price",IF(F10<=G10,"Deep Value / Strong Buy",IF(F10<=H10,"Value / Buy",IF(F10<=I10,"Fair Value / Hold",IF(F10<=J10,"Fully Valued / Trim","Overvalued / Sell"))))) -> 0 | O10: =IF(OR(F10="",F10=0),"N/A",ROUND((L10-F10)/F10*100,1)) -> 0 | P10: Wonderful biscuit franchise at crazy price; 57x PE vs IV ₹2,030-3,281; watchlist ₹2,700-3,600
A11: 9 | B11: Marico | C11: MARICO | D11: NSE | E11: 8.6/10 | G11: 397 | H11: 529 | I11: 661 | J11: 793 | K11: 349 | L11: 421 | M11: 578 | N11: =IF(F11="","Enter Price",IF(F11<=G11,"Deep Value / Strong Buy",IF(F11<=H11,"Value / Buy",IF(F11<=I11,"Fair Value / Hold",IF(F11<=J11,"Fully Valued / Trim","Overvalued / Sell"))))) -> 0 | O11: =IF(OR(F11="",F11=0),"N/A",ROUND((L11-F11)/F11*100,1)) -> 0 | P11: Wonderful consumer franchise (40%+ ROIC) at terrible price; avoid at ₹757, watchlist ₹450
A12: 10 | B12: Page Industries | C12: PAGEIND | D12: NSE | E12: 8.8/10 | G12: 18930 | H12: 25240 | I12: 35336 | J12: 44170 | K12: 11049 | L12: 17549 | M12: 21260 | N12: =IF(F12="","Enter Price",IF(F12<=G12,"Deep Value / Strong Buy",IF(F12<=H12,"Value / Buy",IF(F12<=I12,"Fair Value / Hold",IF(F12<=J12,"Fully Valued / Trim","Overvalued / Sell"))))) -> 0 | O12: =IF(OR(F12="",F12=0),"N/A",ROUND((L12-F12)/F12*100,1)) -> 0 | P12: Jockey India exclusive; elite ROE but zero MoS at ₹35,400; wait for ₹25,000 or below
A13: 11 | B13: United Spirits | C13: UNITDSPR | D13: NSE | E13: 8.5/10 | G13: 559 | H13: 782 | I13: 1118 | J13: 1453 | K13: 551 | L13: 667 | M13: 914 | N13: =IF(F13="","Enter Price",IF(F13<=G13,"Deep Value / Strong Buy",IF(F13<=H13,"Value / Buy",IF(F13<=I13,"Fair Value / Hold",IF(F13<=J13,"Fully Valued / Trim","Overvalued / Sell"))))) -> 0 | O13: =IF(OR(F13="",F13=0),"N/A",ROUND((L13-F13)/F13*100,1)) -> 0 | P13: Wonderful Diageo spirits franchise; triple moat; deeply overvalued at 59x PE; wait ₹782
A14: 12 | B14: Godfrey Phillips India | C14: GODFRYPHLP | D14: NSE | E14: 8.4/10 | G14: 1646 | H14: 1975 | I14: 2305 | J14: 2881 | K14: 1545 | L14: 2230 | M14: 2838 | N14: =IF(F14="","Enter Price",IF(F14<=G14,"Deep Value / Strong Buy",IF(F14<=H14,"Value / Buy",IF(F14<=I14,"Fair Value / Hold",IF(F14<=J14,"Fully Valued / Trim","Overvalued / Sell"))))) -> 0 | O14: =IF(OR(F14="",F14=0),"N/A",ROUND((L14-F14)/F14*100,1)) -> 0 | P14: Buffett-quality cigarette franchise at fair value; wait for <₹1,646 for strong-buy entry
A15: 13 | B15: Eternal | C15: ETERNAL | D15: NSE | E15: 3.2/10 | G15: 40 | H15: 60 | I15: 100 | J15: 150 | K15: 43 | L15: 79 | M15: 152 | N15: Weak Business | O15: =IF(OR(F15="",F15=0),"N/A",ROUND((L15-F15)/F15*100,1)) -> 0 | P15: Overvalued consumer tech; negative EBIT, no moat, SBC-diluted; buy only below ₹40-60
A16: 14 | B16: Cummins India | C16: CUMMINSIND | D16: NSE | E16: 8.9/10 | G16: 1617 | H16: 2426 | I16: 3235 | J16: 4448 | K16: 2103 | L16: 2873 | M16: 3475 | N16: =IF(F16="","Enter Price",IF(F16<=G16,"Deep Value / Strong Buy",IF(F16<=H16,"Value / Buy",IF(F16<=I16,"Fair Value / Hold",IF(F16<=J16,"Fully Valued / Trim","Overvalued / Sell"))))) -> 0 | O16: =IF(OR(F16="",F16=0),"N/A",ROUND((L16-F16)/F16*100,1)) -> 0 | P16: Tech-moated industrial franchise; 36% ROCE, zero debt. 65x PE prices in perfection
A17: 15 | B17: Hindustan Aeronautics | C17: HAL | D17: NSE | E17: 8.5/10 | G17: 2400 | H17: 3200 | I17: 4000 | J17: 4800 | K17: 3351 | L17: 5010 | M17: 6586 | N17: =IF(F17="","Enter Price",IF(F17<=G17,"Deep Value / Strong Buy",IF(F17<=H17,"Value / Buy",IF(F17<=I17,"Fair Value / Hold",IF(F17<=J17,"Fully Valued / Trim","Overvalued / Sell"))))) -> 0 | O17: =IF(OR(F17="",F17=0),"N/A",ROUND((L17-F17)/F17*100,1)) -> 0 | P17: Wonderful govt-monopoly defence business at full price; wait for 25-30% correction
A18: 16 | B18: CIE Automotive India | C18: CIEINDIA | D18: NSE | E18: 7.3/10 | G18: 350 | H18: 450 | I18: 600 | J18: 750 | K18: 458 | L18: 703 | M18: 852 | N18: =IF(F18="","Enter Price",IF(F18<=G18,"Deep Value / Strong Buy",IF(F18<=H18,"Value / Buy",IF(F18<=I18,"Fair Value / Hold",IF(F18<=J18,"Fully Valued / Trim","Overvalued / Sell"))))) -> 0 | O18: =IF(OR(F18="",F18=0),"N/A",ROUND((L18-F18)/F18*100,1)) -> 0 | P18: Good auto-comp supplier; D/E 0.09, improving margins, EV pivot underway
A19: 17 | B19: Aeroflex Industries | C19: AEROFLEX | D19: NSE | E19: 7.4/10 | G19: 100 | H19: 150 | I19: 200 | J19: 260 | K19: 108 | L19: 117 | M19: 148 | N19: =IF(F19="","Enter Price",IF(F19<=G19,"Deep Value / Strong Buy",IF(F19<=H19,"Value / Buy",IF(F19<=I19,"Fair Value / Hold",IF(F19<=J19,"Fully Valued / Trim","Overvalued / Sell"))))) -> 0 | O19: =IF(OR(F19="",F19=0),"N/A",ROUND((L19-F19)/F19*100,1)) -> 0 | P19: Niche metal hose exporter; strong ROCE but priced 2-4x IV at ₹289; wait ₹100-150
A20: 18 | B20: AGI Greenpac | C20: AGI | D20: NSE | E20: 5.7/10 | G20: 325 | H20: 450 | I20: 650 | J20: 850 | K20: 937 | L20: 1367 | M20: 2134 | N20: =IF(F20="","Enter Price",IF(F20<=G20,"Deep Value / Strong Buy",IF(F20<=H20,"Value / Buy",IF(F20<=I20,"Fair Value / Hold",IF(F20<=J20,"Fully Valued / Trim","Overvalued / Sell"))))) -> 0 | O20: =IF(OR(F20="",F20=0),"N/A",ROUND((L20-F20)/F20*100,1)) -> 0 | P20: India's #2 container glass maker; freight-protected oligopoly. HNGIL return threatens OPM
A21: 19 | B21: Zensar Technologies | C21: ZENSARTECH | D21: NSE | E21: 6.7/10 | G21: 450 | H21: 650 | I21: 900 | J21: 1107 | K21: 900 | L21: 1107 | M21: 1316 | N21: =IF(F21="","Enter Price",IF(F21<=G21,"Deep Value / Strong Buy",IF(F21<=H21,"Value / Buy",IF(F21<=I21,"Fair Value / Hold",IF(F21<=J21,"Fully Valued / Trim","Overvalued / Sell"))))) -> 0 | O21: =IF(OR(F21="",F21=0),"N/A",ROUND((L21-F21)/F21*100,1)) -> 0 | P21: Cash-rich mid-tier IT at historically cheap 16x PE; qualified buy with 3-5yr horizon
A22: 20 | B22: Sonata Software | C22: SONATSOFTW | D22: NSE | E22: 6.3/10 | G22: 266 | H22: 380 | I22: 500 | J22: 607 | K22: 380 | L22: 500 | M22: 607 | N22: =IF(F22="","Enter Price",IF(F22<=G22,"Deep Value / Strong Buy",IF(F22<=H22,"Value / Buy",IF(F22<=I22,"Fair Value / Hold",IF(F22<=J22,"Fully Valued / Trim","Overvalued / Sell"))))) -> 0 | O22: =IF(OR(F22="",F22=0),"N/A",ROUND((L22-F22)/F22*100,1)) -> 0 | P22: Microsoft ecosystem IT; margin recovery thesis conditional on EBIT rebound from trough
A23: 21 | B23: CMS Info Systems | C23: CMSINFO | D23: NSE | E23: 7.4/10 | G23: 240 | H23: 320 | I23: 400 | J23: 500 | K23: 354 | L23: 671 | M23: 943 | N23: =IF(F23="","Enter Price",IF(F23<=G23,"Deep Value / Strong Buy",IF(F23<=H23,"Value / Buy",IF(F23<=I23,"Fair Value / Hold",IF(F23<=J23,"Fully Valued / Trim","Overvalued / Sell"))))) -> 0 | O23: =IF(OR(F23="",F23=0),"N/A",ROUND((L23-F23)/F23*100,1)) -> 0 | P23: India's #1 cash mgmt; zero debt, 24%+ ROCE. 3.2:1 asymmetry; accumulate ₹240-320
A24: 22 | B24: Laurus Labs | C24: LAURUSLABS | D24: NSE | E24: 6.3/10 | G24: 250 | H24: 600 | I24: 850 | J24: 1100 | K24: 444 | L24: 673 | M24: 889 | N24: =IF(F24="","Enter Price",IF(F24<=G24,"Deep Value / Strong Buy",IF(F24<=H24,"Value / Buy",IF(F24<=I24,"Fair Value / Hold",IF(F24<=J24,"Fully Valued / Trim","Overvalued / Sell"))))) -> 0 | O24: =IF(OR(F24="",F24=0),"N/A",ROUND((L24-F24)/F24*100,1)) -> 0 | P24: World's largest ARV API supplier + growing CDMO; founder-CEO. Cyclical, capital-intensive
A25: 23 | B25: Kronox Lab Sciences | C25: KRONOX | D25: NSE | E25: 7.7/10 | G25: 100 | H25: 130 | I25: 178 | J25: 338 | K25: 130 | L25: 260 | M25: 338 | N25: =IF(F25="","Enter Price",IF(F25<=G25,"Deep Value / Strong Buy",IF(F25<=H25,"Value / Buy",IF(F25<=I25,"Fair Value / Hold",IF(F25<=J25,"Fully Valued / Trim","Overvalued / Sell"))))) -> 0 | O25: =IF(OR(F25="",F25=0),"N/A",ROUND((L25-F25)/F25*100,1)) -> 0 | P25: High-purity specialty fine chemicals; 30%+ OPM, zero debt. Micro-cap switching cost moat
A26: 24 | B26: NMDC | C26: NMDC | D26: NSE | E26: 6.0/10 | G26: 55 | H26: 74 | I26: 103 | J26: 129 | K26: 135 | L26: 171 | M26: 218 | N26: =IF(F26="","Enter Price",IF(F26<=G26,"Deep Value / Strong Buy",IF(F26<=H26,"Value / Buy",IF(F26<=I26,"Fair Value / Hold",IF(F26<=J26,"Fully Valued / Trim","Overvalued / Sell"))))) -> 0 | O26: =IF(OR(F26="",F26=0),"N/A",ROUND((L26-F26)/F26*100,1)) -> 0 | P26: India's largest iron ore miner; low-cost producer, zero debt. Fair value; accumulate on dips
A27: 25 | B27: Vedanta | C27: VEDL | D27: NSE | E27: 4.8/10 | G27: 400 | H27: 560 | I27: 660 | J27: 853 | K27: 556 | L27: 653 | M27: 853 | N27: Weak Business | O27: =IF(OR(F27="",F27=0),"N/A",ROUND((L27-F27)/F27*100,1)) -> 0 | P27: Commodity conglomerate; governance concerns, high leverage. Overvalued vs normalised earnings
A28: 26 | B28: National Aluminium Company | C28: NATIONALUM | D28: NSE | E28: 6.7/10 | G28: 145 | H28: 243 | I28: 340 | J28: 437 | K28: 188 | L28: 800 | M28: 968 | N28: =IF(F28="","Enter Price",IF(F28<=G28,"Deep Value / Strong Buy",IF(F28<=H28,"Value / Buy",IF(F28<=I28,"Fair Value / Hold",IF(F28<=J28,"Fully Valued / Trim","Overvalued / Sell"))))) -> 0 | O28: =IF(OR(F28="",F28=0),"N/A",ROUND((L28-F28)/F28*100,1)) -> 0 | P28: Low-cost aluminium PSU at cyclical peak; normalised IV ₹188; accumulate at 1.5-2x book
A29: 27 | B29: Bharat Coking Coal | C29: BHARATCOAL | D29: NSE | E29: 4.7/10 | G29: 16 | H29: 25 | I29: 35 | J29: 49 | K29: 21 | L29: 23 | M29: 27 | N29: Weak Business | O29: =IF(OR(F29="",F29=0),"N/A",ROUND((L29-F29)/F29*100,1)) -> 0 | P29: Cyclical PSU coal miner; overvalued vs mid-cycle IV; AVOID, revisit below ₹25
A30: 28 | B30: NTPC | C30: NTPC | D30: NSE | E30: 6.8/10 | G30: 242 | H30: 314 | I30: 386 | J30: 483 | K30: 355 | L30: 531 | M30: 700 | N30: =IF(F30="","Enter Price",IF(F30<=G30,"Deep Value / Strong Buy",IF(F30<=H30,"Value / Buy",IF(F30<=I30,"Fair Value / Hold",IF(F30<=J30,"Fully Valued / Trim","Overvalued / Sell"))))) -> 0 | O30: =IF(OR(F30="",F30=0),"N/A",ROUND((L30-F30)/F30*100,1)) -> 0 | P30: Regulated utility; fully valued at 16.4x PE; HOLD/WAIT, buy below ₹314
A31: 29 | B31: Advait Energy Transitions | C31: ADVAIT | D31: NSE | E31: 5.8/10 | G31: 800 | H31: 1200 | I31: 1800 | J31: 2200 | K31: 853 | L31: 3320 | M31: 5511 | N31: =IF(F31="","Enter Price",IF(F31<=G31,"Deep Value / Strong Buy",IF(F31<=H31,"Value / Buy",IF(F31<=I31,"Fair Value / Hold",IF(F31<=J31,"Fully Valued / Trim","Overvalued / Sell"))))) -> 0 | O31: =IF(OR(F31="",F31=0),"N/A",ROUND((L31-F31)/F31*100,1)) -> 0 | P31: Good EPC growth biz, narrow moat; bimodal valuation; avoid >₹1,200; buy below ₹800
A32: 30 | B32: InterGlobe Aviation | C32: INDIGO | D32: NSE | E32: 6.2/10 | G32: 2800 | H32: 4130 | I32: 5260 | J32: 11839 | K32: 4511 | L32: 8107 | M32: 11839 | N32: =IF(F32="","Enter Price",IF(F32<=G32,"Deep Value / Strong Buy",IF(F32<=H32,"Value / Buy",IF(F32<=I32,"Fair Value / Hold",IF(F32<=J32,"Fully Valued / Trim","Overvalued / Sell"))))) -> 0 | O32: =IF(OR(F32="",F32=0),"N/A",ROUND((L32-F32)/F32*100,1)) -> 0 | P32: India's dominant LCC; fair-priced; accumulate on dips below ₹4,000-4,200
A33: 31 | B33: BLS International | C33: BLS | D33: NSE | E33: 8.4/10 | G33: 188 | H33: 250 | I33: 344 | J33: 470 | K33: 265 | L33: 694 | M33: 937 | N33: =IF(F33="","Enter Price",IF(F33<=G33,"Deep Value / Strong Buy",IF(F33<=H33,"Value / Buy",IF(F33<=I33,"Fair Value / Hold",IF(F33<=J33,"Fully Valued / Trim","Overvalued / Sell"))))) -> 0 | O33: =IF(OR(F33="",F33=0),"N/A",ROUND((L33-F33)/F33*100,1)) -> 0 | P33: Toll-bridge on global visa outsourcing; BUY with 57% MoS to Base IV ₹694
A34: 32 | B34: IRFC | C34: IRFC | D34: NSE | E34: 7.0/10 | G34: 52 | H34: 69 | I34: 86 | J34: 107 | K34: 43 | L34: 60 | M34: 91 | N34: =IF(F34="","Enter Price",IF(F34<=G34,"Deep Value / Strong Buy",IF(F34<=H34,"Value / Buy",IF(F34<=I34,"Fair Value / Hold",IF(F34<=J34,"Fully Valued / Trim","Overvalued / Sell"))))) -> 0 | O34: =IF(OR(F34="",F34=0),"N/A",ROUND((L34-F34)/F34*100,1)) -> 0 | P34: Govt-backed NBFC, zero NPAs; borderline returns at ₹92 (2.14x book); accumulate ₹52-69
A35: 33 | B35: Aelea Commodities | C35: 544213 | D35: BSE | E35: 4.0/10 | G35: 41 | H35: 68 | I35: 115 | J35: 170 | K35: 68 | L35: 113 | M35: 167 | N35: Weak Business | O35: =IF(OR(F35="",F35=0),"N/A",ROUND((L35-F35)/F35*100,1)) -> 0 | P35: No-moat cashew processor; overpriced at 3.9x book; never generated positive FCF; avoid

Sheet Deep Value - Strong Buy
A1: Deep Value - Strong Buy Zone
A2: Companies trading significantly below intrinsic value. Maximum margin of safety. Fat pitch opportunities. (Auto-updates as prices change in 'All Companies' sheet)
A3: Company Name | B3: Ticker | C3: Exchange | D3: Quality | E3: Current Price (Rs) | F3: Deep Value Below (Rs) | G3: Value/Buy Up To (Rs) | H3: Fair Value Up To (Rs) | I3: Overvalued Above (Rs) | J3: Conservative IV (Rs) | K3: Base Case IV (Rs) | L3: Optimistic IV (Rs) | M3: Current Zone | N3: Upside to Base IV (%) | O3: Key Notes
A4: {=_xlfn._xlws.FILTER('All Companies'!B3:P35,'All Companies'!N3:N35="Deep Value / Strong Buy","No companies in this zone currently - enter prices in All Companies sheet")} -> 0 | B4: 0 | C4: 0 | D4: 0 | E4: 0 | F4: 0 | G4: 0 | H4: 0 | I4: 0 | J4: 0 | K4: 0 | L4: 0 | M4: 0 | N4: 0 | O4: 0
A5: 0 | B5: 0 | C5: 0 | D5: 0 | E5: 0 | F5: 0 | G5: 0 | H5: 0 | I5: 0 | J5: 0 | K5: 0 | L5: 0 | M5: 0 | N5: 0 | O5: 0
A6: 0 | B6: 0 | C6: 0 | D6: 0 | E6: 0 | F6: 0 | G6: 0 | H6: 0 | I6: 0 | J6: 0 | K6: 0 | L6: 0 | M6: 0 | N6: 0 | O6: 0
A7: 0 | B7: 0 | C7: 0 | D7: 0 | E7: 0 | F7: 0 | G7: 0 | H7: 0 | I7: 0 | J7: 0 | K7: 0 | L7: 0 | M7: 0 | N7: 0 | O7: 0
A8: 0 | B8: 0 | C8: 0 | D8: 0 | E8: 0 | F8: 0 | G8: 0 | H8: 0 | I8: 0 | J8: 0 | K8: 0 | L8: 0 | M8: 0 | N8: 0 | O8: 0
A9: 0 | B9: 0 | C9: 0 | D9: 0 | E9: 0 | F9: 0 | G9: 0 | H9: 0 | I9: 0 | J9: 0 | K9: 0 | L9: 0 | M9: 0 | N9: 0 | O9: 0
A10: 0 | B10: 0 | C10: 0 | D10: 0 | E10: 0 | F10: 0 | G10: 0 | H10: 0 | I10: 0 | J10: 0 | K10: 0 | L10: 0 | M10: 0 | N10: 0 | O10: 0
A11: 0 | B11: 0 | C11: 0 | D11: 0 | E11: 0 | F11: 0 | G11: 0 | H11: 0 | I11: 0 | J11: 0 | K11: 0 | L11: 0 | M11: 0 | N11: 0 | O11: 0
A12: 0 | B12: 0 | C12: 0 | D12: 0 | E12: 0 | F12: 0 | G12: 0 | H12: 0 | I12: 0 | J12: 0 | K12: 0 | L12: 0 | M12: 0 | N12: 0 | O12: 0
A13: 0 | B13: 0 | C13: 0 | D13: 0 | E13: 0 | F13: 0 | G13: 0 | H13: 0 | I13: 0 | J13: 0 | K13: 0 | L13: 0 | M13: 0 | N13: 0 | O13: 0
A14: 0 | B14: 0 | C14: 0 | D14: 0 | E14: 0 | F14: 0 | G14: 0 | H14: 0 | I14: 0 | J14: 0 | K14: 0 | L14: 0 | M14: 0 | N14: 0 | O14: 0
A15: 0 | B15: 0 | C15: 0 | D15: 0 | E15: 0 | F15: 0 | G15: 0 | H15: 0 | I15: 0 | J15: 0 | K15: 0 | L15: 0 | M15: 0 | N15: 0 | O15: 0
A16: 0 | B16: 0 | C16: 0 | D16: 0 | E16: 0 | F16: 0 | G16: 0 | H16: 0 | I16: 0 | J16: 0 | K16: 0 | L16: 0 | M16: 0 | N16: 0 | O16: 0
... A37: 0 | B37: 0 | C37: 0 | D37: 0 | E37: 0 | F37: 0 | G37: 0 | H37: 0 | I37: 0 | J37: 0 | K37: 0 | L37: 0 | M37: 0 | N37: 0 | O37: 0

Sheet Value - Buy
A1: Value - Buy Zone
A2: Companies trading below fair value with adequate margin of safety. Good entry points. (Auto-updates as prices change in 'All Companies' sheet)
A3: Company Name | B3: Ticker | C3: Exchange | D3: Quality | E3: Current Price (Rs) | F3: Deep Value Below (Rs) | G3: Value/Buy Up To (Rs) | H3: Fair Value Up To (Rs) | I3: Overvalued Above (Rs) | J3: Conservative IV (Rs) | K3: Base Case IV (Rs) | L3: Optimistic IV (Rs) | M3: Current Zone | N3: Upside to Base IV (%) | O3: Key Notes
A4: {=_xlfn._xlws.FILTER('All Companies'!B3:P35,'All Companies'!N3:N35="Value / Buy","No companies in this zone currently - enter prices in All Companies sheet")} -> 0 | B4: 0 | C4: 0 | D4: 0 | E4: 0 | F4: 0 | G4: 0 | H4: 0 | I4: 0 | J4: 0 | K4: 0 | L4: 0 | M4: 0 | N4: 0 | O4: 0
A5: 0 | B5: 0 | C5: 0 | D5: 0 | E5: 0 | F5: 0 | G5: 0 | H5: 0 | I5: 0 | J5: 0 | K5: 0 | L5: 0 | M5: 0 | N5: 0 | O5: 0
A6: 0 | B6: 0 | C6: 0 | D6: 0 | E6: 0 | F6: 0 | G6: 0 | H6: 0 | I6: 0 | J6: 0 | K6: 0 | L6: 0 | M6: 0 | N6: 0 | O6: 0
A7: 0 | B7: 0 | C7: 0 | D7: 0 | E7: 0 | F7: 0 | G7: 0 | H7: 0 | I7: 0 | J7: 0 | K7: 0 | L7: 0 | M7: 0 | N7: 0 | O7: 0
A8: 0 | B8: 0 | C8: 0 | D8: 0 | E8: 0 | F8: 0 | G8: 0 | H8: 0 | I8: 0 | J8: 0 | K8: 0 | L8: 0 | M8: 0 | N8: 0 | O8: 0
A9: 0 | B9: 0 | C9: 0 | D9: 0 | E9: 0 | F9: 0 | G9: 0 | H9: 0 | I9: 0 | J9: 0 | K9: 0 | L9: 0 | M9: 0 | N9: 0 | O9: 0
A10: 0 | B10: 0 | C10: 0 | D10: 0 | E10: 0 | F10: 0 | G10: 0 | H10: 0 | I10: 0 | J10: 0 | K10: 0 | L10: 0 | M10: 0 | N10: 0 | O10: 0
A11: 0 | B11: 0 | C11: 0 | D11: 0 | E11: 0 | F11: 0 | G11: 0 | H11: 0 | I11: 0 | J11: 0 | K11: 0 | L11: 0 | M11: 0 | N11: 0 | O11: 0
A12: 0 | B12: 0 | C12: 0 | D12: 0 | E12: 0 | F12: 0 | G12: 0 | H12: 0 | I12: 0 | J12: 0 | K12: 0 | L12: 0 | M12: 0 | N12: 0 | O12: 0
A13: 0 | B13: 0 | C13: 0 | D13: 0 | E13: 0 | F13: 0 | G13: 0 | H13: 0 | I13: 0 | J13: 0 | K13: 0 | L13: 0 | M13: 0 | N13: 0 | O13: 0
A14: 0 | B14: 0 | C14: 0 | D14: 0 | E14: 0 | F14: 0 | G14: 0 | H14: 0 | I14: 0 | J14: 0 | K14: 0 | L14: 0 | M14: 0 | N14: 0 | O14: 0
A15: 0 | B15: 0 | C15: 0 | D15: 0 | E15: 0 | F15: 0 | G15: 0 | H15: 0 | I15: 0 | J15: 0 | K15: 0 | L15: 0 | M15: 0 | N15: 0 | O15: 0
A16: 0 | B16: 0 | C16: 0 | D16: 0 | E16: 0 | F16: 0 | G16: 0 | H16: 0 | I16: 0 | J16: 0 | K16: 0 | L16: 0 | M16: 0 | N16: 0 | O16: 0
... A37: 0 | B37: 0 | C37: 0 | D37: 0 | E37: 0 | F37: 0 | G37: 0 | H37: 0 | I37: 0 | J37: 0 | K37: 0 | L37: 0 | M37: 0 | N37: 0 | O37: 0

Sheet Fair Value - Hold
A1: Fair Value - Hold Zone
A2: Companies trading around intrinsic value. Hold if owned, don't initiate new positions. (Auto-updates as prices change in 'All Companies' sheet)
A3: Company Name | B3: Ticker | C3: Exchange | D3: Quality | E3: Current Price (Rs) | F3: Deep Value Below (Rs) | G3: Value/Buy Up To (Rs) | H3: Fair Value Up To (Rs) | I3: Overvalued Above (Rs) | J3: Conservative IV (Rs) | K3: Base Case IV (Rs) | L3: Optimistic IV (Rs) | M3: Current Zone | N3: Upside to Base IV (%) | O3: Key Notes
A4: {=_xlfn._xlws.FILTER('All Companies'!B3:P35,'All Companies'!N3:N35="Fair Value / Hold","No companies in this zone currently - enter prices in All Companies sheet")} -> 0 | B4: 0 | C4: 0 | D4: 0 | E4: 0 | F4: 0 | G4: 0 | H4: 0 | I4: 0 | J4: 0 | K4: 0 | L4: 0 | M4: 0 | N4: 0 | O4: 0
A5: 0 | B5: 0 | C5: 0 | D5: 0 | E5: 0 | F5: 0 | G5: 0 | H5: 0 | I5: 0 | J5: 0 | K5: 0 | L5: 0 | M5: 0 | N5: 0 | O5: 0
A6: 0 | B6: 0 | C6: 0 | D6: 0 | E6: 0 | F6: 0 | G6: 0 | H6: 0 | I6: 0 | J6: 0 | K6: 0 | L6: 0 | M6: 0 | N6: 0 | O6: 0
A7: 0 | B7: 0 | C7: 0 | D7: 0 | E7: 0 | F7: 0 | G7: 0 | H7: 0 | I7: 0 | J7: 0 | K7: 0 | L7: 0 | M7: 0 | N7: 0 | O7: 0
A8: 0 | B8: 0 | C8: 0 | D8: 0 | E8: 0 | F8: 0 | G8: 0 | H8: 0 | I8: 0 | J8: 0 | K8: 0 | L8: 0 | M8: 0 | N8: 0 | O8: 0
A9: 0 | B9: 0 | C9: 0 | D9: 0 | E9: 0 | F9: 0 | G9: 0 | H9: 0 | I9: 0 | J9: 0 | K9: 0 | L9: 0 | M9: 0 | N9: 0 | O9: 0
A10: 0 | B10: 0 | C10: 0 | D10: 0 | E10: 0 | F10: 0 | G10: 0 | H10: 0 | I10: 0 | J10: 0 | K10: 0 | L10: 0 | M10: 0 | N10: 0 | O10: 0
A11: 0 | B11: 0 | C11: 0 | D11: 0 | E11: 0 | F11: 0 | G11: 0 | H11: 0 | I11: 0 | J11: 0 | K11: 0 | L11: 0 | M11: 0 | N11: 0 | O11: 0
A12: 0 | B12: 0 | C12: 0 | D12: 0 | E12: 0 | F12: 0 | G12: 0 | H12: 0 | I12: 0 | J12: 0 | K12: 0 | L12: 0 | M12: 0 | N12: 0 | O12: 0
A13: 0 | B13: 0 | C13: 0 | D13: 0 | E13: 0 | F13: 0 | G13: 0 | H13: 0 | I13: 0 | J13: 0 | K13: 0 | L13: 0 | M13: 0 | N13: 0 | O13: 0
A14: 0 | B14: 0 | C14: 0 | D14: 0 | E14: 0 | F14: 0 | G14: 0 | H14: 0 | I14: 0 | J14: 0 | K14: 0 | L14: 0 | M14: 0 | N14: 0 | O14: 0
A15: 0 | B15: 0 | C15: 0 | D15: 0 | E15: 0 | F15: 0 | G15: 0 | H15: 0 | I15: 0 | J15: 0 | K15: 0 | L15: 0 | M15: 0 | N15: 0 | O15: 0
A16: 0 | B16: 0 | C16: 0 | D16: 0 | E16: 0 | F16: 0 | G16: 0 | H16: 0 | I16: 0 | J16: 0 | K16: 0 | L16: 0 | M16: 0 | N16: 0 | O16: 0
... A37: 0 | B37: 0 | C37: 0 | D37: 0 | E37: 0 | F37: 0 | G37: 0 | H37: 0 | I37: 0 | J37: 0 | K37: 0 | L37: 0 | M37: 0 | N37: 0 | O37: 0

Sheet Fully Valued - Trim
A1: Fully Valued - Trim Zone
A2: Companies trading above base-case intrinsic value. Consider trimming positions. (Auto-updates as prices change in 'All Companies' sheet)
A3: Company Name | B3: Ticker | C3: Exchange | D3: Quality | E3: Current Price (Rs) | F3: Deep Value Below (Rs) | G3: Value/Buy Up To (Rs) | H3: Fair Value Up To (Rs) | I3: Overvalued Above (Rs) | J3: Conservative IV (Rs) | K3: Base Case IV (Rs) | L3: Optimistic IV (Rs) | M3: Current Zone | N3: Upside to Base IV (%) | O3: Key Notes
A4: {=_xlfn._xlws.FILTER('All Companies'!B3:P35,'All Companies'!N3:N35="Fully Valued / Trim","No companies in this zone currently - enter prices in All Companies sheet")} -> 0 | B4: 0 | C4: 0 | D4: 0 | E4: 0 | F4: 0 | G4: 0 | H4: 0 | I4: 0 | J4: 0 | K4: 0 | L4: 0 | M4: 0 | N4: 0 | O4: 0
A5: 0 | B5: 0 | C5: 0 | D5: 0 | E5: 0 | F5: 0 | G5: 0 | H5: 0 | I5: 0 | J5: 0 | K5: 0 | L5: 0 | M5: 0 | N5: 0 | O5: 0
A6: 0 | B6: 0 | C6: 0 | D6: 0 | E6: 0 | F6: 0 | G6: 0 | H6: 0 | I6: 0 | J6: 0 | K6: 0 | L6: 0 | M6: 0 | N6: 0 | O6: 0
A7: 0 | B7: 0 | C7: 0 | D7: 0 | E7: 0 | F7: 0 | G7: 0 | H7: 0 | I7: 0 | J7: 0 | K7: 0 | L7: 0 | M7: 0 | N7: 0 | O7: 0
A8: 0 | B8: 0 | C8: 0 | D8: 0 | E8: 0 | F8: 0 | G8: 0 | H8: 0 | I8: 0 | J8: 0 | K8: 0 | L8: 0 | M8: 0 | N8: 0 | O8: 0
A9: 0 | B9: 0 | C9: 0 | D9: 0 | E9: 0 | F9: 0 | G9: 0 | H9: 0 | I9: 0 | J9: 0 | K9: 0 | L9: 0 | M9: 0 | N9: 0 | O9: 0
A10: 0 | B10: 0 | C10: 0 | D10: 0 | E10: 0 | F10: 0 | G10: 0 | H10: 0 | I10: 0 | J10: 0 | K10: 0 | L10: 0 | M10: 0 | N10: 0 | O10: 0
A11: 0 | B11: 0 | C11: 0 | D11: 0 | E11: 0 | F11: 0 | G11: 0 | H11: 0 | I11: 0 | J11: 0 | K11: 0 | L11: 0 | M11: 0 | N11: 0 | O11: 0
A12: 0 | B12: 0 | C12: 0 | D12: 0 | E12: 0 | F12: 0 | G12: 0 | H12: 0 | I12: 0 | J12: 0 | K12: 0 | L12: 0 | M12: 0 | N12: 0 | O12: 0
A13: 0 | B13: 0 | C13: 0 | D13: 0 | E13: 0 | F13: 0 | G13: 0 | H13: 0 | I13: 0 | J13: 0 | K13: 0 | L13: 0 | M13: 0 | N13: 0 | O13: 0
A14: 0 | B14: 0 | C14: 0 | D14: 0 | E14: 0 | F14: 0 | G14: 0 | H14: 0 | I14: 0 | J14: 0 | K14: 0 | L14: 0 | M14: 0 | N14: 0 | O14: 0
A15: 0 | B15: 0 | C15: 0 | D15: 0 | E15: 0 | F15: 0 | G15: 0 | H15: 0 | I15: 0 | J15: 0 | K15: 0 | L15: 0 | M15: 0 | N15: 0 | O15: 0
A16: 0 | B16: 0 | C16: 0 | D16: 0 | E16: 0 | F16: 0 | G16: 0 | H16: 0 | I16: 0 | J16: 0 | K16: 0 | L16: 0 | M16: 0 | N16: 0 | O16: 0
... A37: 0 | B37: 0 | C37: 0 | D37: 0 | E37: 0 | F37: 0 | G37: 0 | H37: 0 | I37: 0 | J37: 0 | K37: 0 | L37: 0 | M37: 0 | N37: 0 | O37: 0

Sheet Overvalued - Sell
A1: Overvalued - Sell Zone
A2: Companies significantly above all intrinsic value estimates. Sell or avoid entirely. (Auto-updates as prices change in 'All Companies' sheet)
A3: Company Name | B3: Ticker | C3: Exchange | D3: Quality | E3: Current Price (Rs) | F3: Deep Value Below (Rs) | G3: Value/Buy Up To (Rs) | H3: Fair Value Up To (Rs) | I3: Overvalued Above (Rs) | J3: Conservative IV (Rs) | K3: Base Case IV (Rs) | L3: Optimistic IV (Rs) | M3: Current Zone | N3: Upside to Base IV (%) | O3: Key Notes
A4: {=_xlfn._xlws.FILTER('All Companies'!B3:P35,'All Companies'!N3:N35="Overvalued / Sell","No companies in this zone currently - enter prices in All Companies sheet")} -> 0 | B4: 0 | C4: 0 | D4: 0 | E4: 0 | F4: 0 | G4: 0 | H4: 0 | I4: 0 | J4: 0 | K4: 0 | L4: 0 | M4: 0 | N4: 0 | O4: 0
A5: 0 | B5: 0 | C5: 0 | D5: 0 | E5: 0 | F5: 0 | G5: 0 | H5: 0 | I5: 0 | J5: 0 | K5: 0 | L5: 0 | M5: 0 | N5: 0 | O5: 0
A6: 0 | B6: 0 | C6: 0 | D6: 0 | E6: 0 | F6: 0 | G6: 0 | H6: 0 | I6: 0 | J6: 0 | K6: 0 | L6: 0 | M6: 0 | N6: 0 | O6: 0
A7: 0 | B7: 0 | C7: 0 | D7: 0 | E7: 0 | F7: 0 | G7: 0 | H7: 0 | I7: 0 | J7: 0 | K7: 0 | L7: 0 | M7: 0 | N7: 0 | O7: 0
A8: 0 | B8: 0 | C8: 0 | D8: 0 | E8: 0 | F8: 0 | G8: 0 | H8: 0 | I8: 0 | J8: 0 | K8: 0 | L8: 0 | M8: 0 | N8: 0 | O8: 0
A9: 0 | B9: 0 | C9: 0 | D9: 0 | E9: 0 | F9: 0 | G9: 0 | H9: 0 | I9: 0 | J9: 0 | K9: 0 | L9: 0 | M9: 0 | N9: 0 | O9: 0
A10: 0 | B10: 0 | C10: 0 | D10: 0 | E10: 0 | F10: 0 | G10: 0 | H10: 0 | I10: 0 | J10: 0 | K10: 0 | L10: 0 | M10: 0 | N10: 0 | O10: 0
A11: 0 | B11: 0 | C11: 0 | D11: 0 | E11: 0 | F11: 0 | G11: 0 | H11: 0 | I11: 0 | J11: 0 | K11: 0 | L11: 0 | M11: 0 | N11: 0 | O11: 0
A12: 0 | B12: 0 | C12: 0 | D12: 0 | E12: 0 | F12: 0 | G12: 0 | H12: 0 | I12: 0 | J12: 0 | K12: 0 | L12: 0 | M12: 0 | N12: 0 | O12: 0
A13: 0 | B13: 0 | C13: 0 | D13: 0 | E13: 0 | F13: 0 | G13: 0 | H13: 0 | I13: 0 | J13: 0 | K13: 0 | L13: 0 | M13: 0 | N13: 0 | O13: 0
A14: 0 | B14: 0 | C14: 0 | D14: 0 | E14: 0 | F14: 0 | G14: 0 | H14: 0 | I14: 0 | J14: 0 | K14: 0 | L14: 0 | M14: 0 | N14: 0 | O14: 0
A15: 0 | B15: 0 | C15: 0 | D15: 0 | E15: 0 | F15: 0 | G15: 0 | H15: 0 | I15: 0 | J15: 0 | K15: 0 | L15: 0 | M15: 0 | N15: 0 | O15: 0
A16: 0 | B16: 0 | C16: 0 | D16: 0 | E16: 0 | F16: 0 | G16: 0 | H16: 0 | I16: 0 | J16: 0 | K16: 0 | L16: 0 | M16: 0 | N16: 0 | O16: 0
... A37: 0 | B37: 0 | C37: 0 | D37: 0 | E37: 0 | F37: 0 | G37: 0 | H37: 0 | I37: 0 | J37: 0 | K37: 0 | L37: 0 | M37: 0 | N37: 0 | O37: 0

Sheet Weak Business
A1: Weak Business Zone
A2: Fundamentally broken businesses. No price is cheap enough. Never buy. (Auto-updates as prices change in 'All Companies' sheet)
A3: Company Name | B3: Ticker | C3: Exchange | D3: Quality | E3: Current Price (Rs) | F3: Deep Value Below (Rs) | G3: Value/Buy Up To (Rs) | H3: Fair Value Up To (Rs) | I3: Overvalued Above (Rs) | J3: Conservative IV (Rs) | K3: Base Case IV (Rs) | L3: Optimistic IV (Rs) | M3: Current Zone | N3: Upside to Base IV (%) | O3: Key Notes
A4: {=_xlfn._xlws.FILTER('All Companies'!B3:P35,'All Companies'!N3:N35="Weak Business","No companies in this zone currently - enter prices in All Companies sheet")} -> 0 | B4: 0 | C4: 0 | D4: 0 | E4: 0 | F4: 0 | G4: 0 | H4: 0 | I4: 0 | J4: 0 | K4: 0 | L4: 0 | M4: 0 | N4: 0 | O4: 0
A5: 0 | B5: 0 | C5: 0 | D5: 0 | E5: 0 | F5: 0 | G5: 0 | H5: 0 | I5: 0 | J5: 0 | K5: 0 | L5: 0 | M5: 0 | N5: 0 | O5: 0
A6: 0 | B6: 0 | C6: 0 | D6: 0 | E6: 0 | F6: 0 | G6: 0 | H6: 0 | I6: 0 | J6: 0 | K6: 0 | L6: 0 | M6: 0 | N6: 0 | O6: 0
A7: 0 | B7: 0 | C7: 0 | D7: 0 | E7: 0 | F7: 0 | G7: 0 | H7: 0 | I7: 0 | J7: 0 | K7: 0 | L7: 0 | M7: 0 | N7: 0 | O7: 0
A8: 0 | B8: 0 | C8: 0 | D8: 0 | E8: 0 | F8: 0 | G8: 0 | H8: 0 | I8: 0 | J8: 0 | K8: 0 | L8: 0 | M8: 0 | N8: 0 | O8: 0
A9: 0 | B9: 0 | C9: 0 | D9: 0 | E9: 0 | F9: 0 | G9: 0 | H9: 0 | I9: 0 | J9: 0 | K9: 0 | L9: 0 | M9: 0 | N9: 0 | O9: 0
A10: 0 | B10: 0 | C10: 0 | D10: 0 | E10: 0 | F10: 0 | G10: 0 | H10: 0 | I10: 0 | J10: 0 | K10: 0 | L10: 0 | M10: 0 | N10: 0 | O10: 0
A11: 0 | B11: 0 | C11: 0 | D11: 0 | E11: 0 | F11: 0 | G11: 0 | H11: 0 | I11: 0 | J11: 0 | K11: 0 | L11: 0 | M11: 0 | N11: 0 | O11: 0
A12: 0 | B12: 0 | C12: 0 | D12: 0 | E12: 0 | F12: 0 | G12: 0 | H12: 0 | I12: 0 | J12: 0 | K12: 0 | L12: 0 | M12: 0 | N12: 0 | O12: 0
A13: 0 | B13: 0 | C13: 0 | D13: 0 | E13: 0 | F13: 0 | G13: 0 | H13: 0 | I13: 0 | J13: 0 | K13: 0 | L13: 0 | M13: 0 | N13: 0 | O13: 0
A14: 0 | B14: 0 | C14: 0 | D14: 0 | E14: 0 | F14: 0 | G14: 0 | H14: 0 | I14: 0 | J14: 0 | K14: 0 | L14: 0 | M14: 0 | N14: 0 | O14: 0
A15: 0 | B15: 0 | C15: 0 | D15: 0 | E15: 0 | F15: 0 | G15: 0 | H15: 0 | I15: 0 | J15: 0 | K15: 0 | L15: 0 | M15: 0 | N15: 0 | O15: 0
A16: 0 | B16: 0 | C16: 0 | D16: 0 | E16: 0 | F16: 0 | G16: 0 | H16: 0 | I16: 0 | J16: 0 | K16: 0 | L16: 0 | M16: 0 | N16: 0 | O16: 0
... A37: 0 | B37: 0 | C37: 0 | D37: 0 | E37: 0 | F37: 0 | G37: 0 | H37: 0 | I37: 0 | J37: 0 | K37: 0 | L37: 0 | M37: 0 | N37: 0 | O37: 0

Sheet Summary Stats
B1: Portfolio Zone Distribution
B3: Zone | C3: Count | D3: Description
B4: Deep Value / Strong Buy | C4: =COUNTIF('All Companies'!N3:N35,"Deep Value / Strong Buy") -> 0 | D4: Maximum margin of safety - fat pitch opportunities
B5: Value / Buy | C5: =COUNTIF('All Companies'!N3:N35,"Value / Buy") -> 0 | D5: Below fair value - good entry points
B6: Fair Value / Hold | C6: =COUNTIF('All Companies'!N3:N35,"Fair Value / Hold") -> 0 | D6: Around intrinsic value - hold, don't buy
B7: Fully Valued / Trim | C7: =COUNTIF('All Companies'!N3:N35,"Fully Valued / Trim") -> 0 | D7: Above intrinsic value - consider trimming
B8: Overvalued / Sell | C8: =COUNTIF('All Companies'!N3:N35,"Overvalued / Sell") -> 0 | D8: Significantly overvalued - sell or avoid
B9: Weak Business | C9: =COUNTIF('All Companies'!N3:N35,"Weak Business") -> 0 | D9: Fundamentally broken - never buy
B10: Enter Price | C10: =COUNTIF('All Companies'!N3:N35,"Enter Price") -> 0 | D10: Price not yet entered
B11: TOTAL | C11: =SUM(C4:C10) -> 0
B13: HIGHEST CONVICTION BUSINESSES (Ranked by Fundamental Quality)
B14: Company | C14: Quality | D14: Business Moat & Fundamentals
B15: Cummins India | C15: 8.9/10 | D15: Tech-moated industrial franchise; 36% ROCE, zero debt
B16: Page Industries | C16: 8.8/10 | D16: Jockey India exclusive; elite ROE but zero MoS at ₹35,400; wait for ₹25,000 or below
B17: Britannia Industries | C17: 8.7/10 | D17: Wonderful biscuit franchise at crazy price; 57x PE vs IV ₹2,030-3,281; watchlist ₹2,700-3,600
B18: Asian Paints | C18: 8.6/10 | D18: India's finest paint franchise; 62x PE vs IV ₹922-1,638; AVOID, buy below ₹922
B19: Marico | C19: 8.6/10 | D19: Wonderful consumer franchise (40%+ ROIC) at terrible price; avoid at ₹757, watchlist ₹450
B20: Hindustan Aeronautics | C20: 8.5/10 | D20: Wonderful govt-monopoly defence business at full price; wait for 25-30% correction
B21: United Spirits | C21: 8.5/10 | D21: Wonderful Diageo spirits franchise; triple moat; deeply overvalued at 59x PE; wait ₹782
B22: BLS International | C22: 8.4/10 | D22: Toll-bridge on global visa outsourcing; BUY with 57% MoS to Base IV ₹694
B23: Godfrey Phillips India | C23: 8.4/10 | D23: Buffett-quality cigarette franchise at fair value; wait for <₹1,646 for strong-buy entry
B24: JSW Dulux | C24: 7.8/10 | D24: Elite 42% ROCE paint franchise; at 2x IV post-divestment; watchlist ₹1,440-1,800
B25: Kronox Lab Sciences | C25: 7.7/10 | D25: High-purity specialty fine chemicals; 30%+ OPM, zero debt
